{
  "plugins": {
    "blink.cmp": {
      "rev": "b19413d",
      "src": "https://github.com/saghen/blink.cmp",
      "version": ">=0.0.0"
    },
    "kanagawa.nvim": {
      "rev": "aef7f5c",
      "src": "https://github.com/rebelot/kanagawa.nvim"
    },
    "mini.ai": {
      "rev": "bfb26d9",
      "src": "https://github.com/nvim-mini/mini.ai"
    },
    "mini.icons": {
      "rev": "ff2e4f1",
      "src": "https://github.com/nvim-mini/mini.icons"
    },
    "mini.surround": {
      "rev": "88c5229",
      "src": "https://github.com/nvim-mini/mini.surround"
    },
    "nvim-autopairs": {
      "rev": "c2a0dd0",
      "src": "https://github.com/windwp/nvim-autopairs"
    },
    "nvim-lspconfig": {
      "rev": "d20d83b",
      "src": "https://github.com/neovim/nvim-lspconfig"
    },
    "oil.nvim": {
      "rev": "756dec8",
      "src": "https://github.com/stevearc/oil.nvim"
    },
    "pick-resession.nvim": {
      "rev": "3bd9b6a",
      "src": "https://github.com/scottmckendry/pick-resession.nvim"
    },
    "plenary.nvim": {
      "rev": "b9fd522",
      "src": "https://github.com/nvim-lua/plenary.nvim"
    },
    "resession.nvim": {
      "rev": "05adc14",
      "src": "https://github.com/stevearc/resession.nvim"
    },
    "telescope.nvim": {
      "rev": "e709d31",
      "src": "https://github.com/nvim-telescope/telescope.nvim"
    },
    "todo-comments.nvim": {
      "rev": "31e3c38",
      "src": "https://github.com/folke/todo-comments.nvim"
    }
  }
}